lofarantpos/__init__.py
lofarantpos/db.py
lofarantpos/geo.py
lofarantpos/plotutil.py
lofarantpos/share/lofarantpos/etrs-antenna-positions.csv
lofarantpos/share/lofarantpos/etrs-phase-centres.csv
lofarantpos/share/lofarantpos/hba-rotations.csv
lofarantpos/share/lofarantpos/lora_detectors.csv
lofarantpos/share/lofarantpos/normal_vectors.dat
lofarantpos/share/lofarantpos/rotation_matrices.dat
lofarantpos/share/lofarantpos/stationinfo.csv
lofarantpos-0.7.2.dist-info/licenses/LICENSE
lofarantpos-0.7.2.dist-info/METADATA
lofarantpos-0.7.2.dist-info/WHEEL
lofarantpos-0.7.2.dist-info/top_level.txt
lofarantpos-0.7.2.dist-info/RECORD
