Metadata-Version: 2.4
Name: lofarantpos
Version: 0.7.2
Summary: Access, query, and manipulate LOFAR antenna positions
Author-email: Tammo Jan Dijkema <dijkema@astron.nl>, "M.A. Brentjens" <brentjens@astron.nl>
License: Apache-2.0
Project-URL: Homepage, https://github.com/lofar-astron/lofar-antenna-positions
Classifier: License :: OSI Approved :: Apache Software License
Classifier: Operating System :: OS Independent
Classifier: Programming Language :: Python :: 2
Classifier: Programming Language :: Python :: 3
Requires-Python: >=3.7
License-File: LICENSE
Requires-Dist: numpy
Requires-Dist: matplotlib
Requires-Dist: pathlib
Requires-Dist: tilemapbase
Dynamic: license-file
